LICENSE
README.md
setup.py
pycordia/__init__.py
pycordia/_interactions.py
pycordia/api.py
pycordia/client.py
pycordia/errors.py
pycordia/events.py
pycordia/utils.py
pycordia/websocket.py
pycordia.egg-info/PKG-INFO
pycordia.egg-info/SOURCES.txt
pycordia.egg-info/dependency_links.txt
pycordia.egg-info/requires.txt
pycordia.egg-info/top_level.txt
pycordia/models/__init__.py
pycordia/models/channel.py
pycordia/models/embed.py
pycordia/models/guild.py
pycordia/models/message.py
pycordia/models/presence.py
pycordia/models/user.py